fastsettings/__init__.py
fastsettings/admin.py
fastsettings/apps.py
fastsettings/models.py
fastsettings/projectsettings.py
fastsettings/tests.py
fastsettings/migrations/0001_initial.py
fastsettings/migrations/__init__.py
t/__init__.py
t/settings.py
t/urls.py
t/wsgi.py
django_fastsettings-0.5.dist-info/LICENSE
django_fastsettings-0.5.dist-info/METADATA
django_fastsettings-0.5.dist-info/WHEEL
django_fastsettings-0.5.dist-info/top_level.txt
django_fastsettings-0.5.dist-info/RECORD
